keysvalues/__init__.py
keysvalues-2.0.7.dist-info/WHEEL
keysvalues-2.0.7.dist-info/METADATA
keysvalues-2.0.7.dist-info/RECORD
