Metadata-Version: 2.3
Name: keysvalues
Version: 2.0.7
Summary: Functions for, instead of values and key functions, key-value pairs.
Keywords: key,keys,sort,sorting
Author: John Dawson
Author-email: John Dawson <john.a.dawson@proton.me>
License:                     GNU GENERAL PUBLIC LICENSE
Maintainer: John Dawson
Maintainer-email: John Dawson <john.a.dawson@proton.me>
Project-URL: Documentation, https://github.com/JohnADawson/keysvalues/blob/master/src/keysvalues/__init__.py
Project-URL: Homepage, https://github.com/JohnADawson/keysvalues
